poppy_torso/__init__.py
poppy_torso/_version.py
poppy_torso/poppy_torso.py
poppy_torso/poppy_torso.urdf
poppy_torso/configuration/poppy_torso.json
poppy_torso/media/sounds/error.wav
poppy_torso/primitives/__init__.py
poppy_torso/primitives/dance.py
poppy_torso/primitives/idle.py
poppy_torso/primitives/interaction.py
poppy_torso/primitives/posture.py
poppy_torso/primitives/safe.py
poppy_torso/utils/__init__.py
poppy_torso/utils/min_jerk.py
poppy_torso/vrep-scene/poppy_torso.ttt
poppy_torso-3.0.0.dist-info/LICENSE
poppy_torso-3.0.0.dist-info/METADATA
poppy_torso-3.0.0.dist-info/WHEEL
poppy_torso-3.0.0.dist-info/top_level.txt
poppy_torso-3.0.0.dist-info/RECORD
