Metadata-Version: 2.1
Name: poppy-torso
Version: 3.0.0
Summary: Poppy Torso Software Library
Home-page: https://poppy-project.org
Author: Poppy Station
Author-email: dev@poppy-station.org
License: GNU GENERAL PUBLIC LICENSE Version 3
Platform: UNKNOWN
Requires-Dist: pypot (>=4.0.0)
